pyews/__init__.py
pyews/__main__.py
pyews/ews.py
pyews/core/__init__.py
pyews/core/authentication.py
pyews/core/core.py
pyews/core/endpoints.py
pyews/core/exchangeversion.py
pyews/core/oauth2connector.py
pyews/data/logging.yml
pyews/endpoint/__init__.py
pyews/endpoint/adddelegate.py
pyews/endpoint/convertid.py
pyews/endpoint/createfolder.py
pyews/endpoint/createitem.py
pyews/endpoint/deletefolder.py
pyews/endpoint/deleteitem.py
pyews/endpoint/executesearch.py
pyews/endpoint/expanddl.py
pyews/endpoint/findfolder.py
pyews/endpoint/finditem.py
pyews/endpoint/getattachment.py
pyews/endpoint/getdomainsettings.py
pyews/endpoint/gethiddeninboxrules.py
pyews/endpoint/getinboxrules.py
pyews/endpoint/getitem.py
pyews/endpoint/getsearchablemailboxes.py
pyews/endpoint/getserviceconfiguration.py
pyews/endpoint/getusersettings.py
pyews/endpoint/resolvenames.py
pyews/endpoint/searchmailboxes.py
pyews/endpoint/syncfolderhierarchy.py
pyews/endpoint/syncfolderitems.py
pyews/service/__init__.py
pyews/service/autodiscover.py
pyews/service/base.py
pyews/service/operation.py
pyews/utils/__init__.py
pyews/utils/attributes.py
pyews/utils/exceptions.py
pyews/utils/logger.py
pyews/utils/searchfilter.py
py_ews-3.2.0.dist-info/LICENSE
py_ews-3.2.0.dist-info/METADATA
py_ews-3.2.0.dist-info/WHEEL
py_ews-3.2.0.dist-info/entry_points.txt
py_ews-3.2.0.dist-info/top_level.txt
py_ews-3.2.0.dist-info/RECORD
