Metadata-Version: 2.1
Name: py-ews
Version: 3.2.0
Summary: A Python package to interact with both on-premises and Office 365 Exchange Web Services
Home-page: https://github.com/swimlane/pyews
Author: Swimlane
Author-email: info@swimlane.com
License: MIT
Keywords: ews,exchange,office365,email,ediscovery,swimlane
Platform: UNKNOWN
Requires-Python: >=3.6, <4
License-File: LICENSE
Requires-Dist: requests (==2.27.1)
Requires-Dist: bs4 (==0.0.1)
Requires-Dist: lxml (==4.7.1)
Requires-Dist: pyyaml (==6.0.0)
Requires-Dist: xmltodict (==0.12.0)
Requires-Dist: m2r (==0.2.1)
Requires-Dist: fire (==0.4.0)
Requires-Dist: oauthlib (==3.2.0)
Requires-Dist: mistune (==0.8.4)
Requires-Dist: requests-oauthlib (==1.3.1)
